[
  {
     "text": "Started working on the app-ideas repository",
     "date": "February 25 2021",
     "category": {
        "tag": "app-ideas",
        "color": "#FFDB14"
     },
     "link": {
        "url": "https://github.com/florinpop17/app-ideas",
        "text": "Check it out on GitHub"
     }
  },
  {
     "text": "Started the Weekly Coding Challenge program",
     "date": "March 04 2021",
     "category": {
        "tag": "blog",
        "color": "#e17b77"
     },
     "link": {
        "url": "https://florin-pop/blog/2019/03/weekly-coding-challenge/",
        "text": "Check it out here"
     }
  },
  {
     "text": "Got 1.000 followers on Twitter",
     "date": "March 07 2021",
     "category": {
        "tag": "twitter",
        "color": "#1DA1F2"
     },
     "link": {
        "url": "https://twitter.com/florinpop1705",
        "text": "See profile"
     }
  },
  {
     "text": "I published my first article in the FreeCodeCamp Medium Publication",
     "date": "March 18 2021",
     "category": {
        "tag": "medium",
        "color": "#018f69"
     },
     "link": {
        "url": "https://medium.freecodecamp.org/how-to-build-a-double-slider-sign-in-and-sign-up-form-6a5d03612a34",
        "text": "Check it out here"
     }
  },
  {
     "text": "Over 12.000 views in a single day on my Medium posts",
     "date": "April 05 2021",
     "category": {
        "tag": "medium",
        "color": "#018f69"
     },
     "link": {
        "url": "https://medium.com/@popflorin1705",
        "text": "See profile"
     }
  },
  {
    "text": "Started working on the app-ideas repository",
    "date": "February 25 2021",
    "category": {
       "tag": "app-ideas",
       "color": "#FFDB14"
    },
    "link": {
       "url": "https://github.com/florinpop17/app-ideas",
       "text": "Check it out on GitHub"
    }
 },
 {
    "text": "Started the Weekly Coding Challenge program",
    "date": "March 04 2021",
    "category": {
       "tag": "blog",
       "color": "#e17b77"
    },
    "link": {
       "url": "https://florin-pop/blog/2019/03/weekly-coding-challenge/",
       "text": "Check it out here"
    }
 },
 {
    "text": "Got 1.000 followers on Twitter",
    "date": "March 07 2021",
    "category": {
       "tag": "twitter",
       "color": "#1DA1F2"
    },
    "link": {
       "url": "https://twitter.com/florinpop1705",
       "text": "See profile"
    }
 },
 {
    "text": "I published my first article in the FreeCodeCamp Medium Publication",
    "date": "March 18 2021",
    "category": {
       "tag": "medium",
       "color": "#018f69"
    },
    "link": {
       "url": "https://medium.freecodecamp.org/how-to-build-a-double-slider-sign-in-and-sign-up-form-6a5d03612a34",
       "text": "Check it out here"
    }
 },
 {
    "text": "Over 12.000 views in a single day on my Medium posts",
    "date": "April 05 2021",
    "category": {
       "tag": "medium",
       "color": "#018f69"
    },
    "link": {
       "url": "https://medium.com/@popflorin1705",
       "text": "See profile"
    }
 }
]